{"id": "ae71f178-cbe8-466a-b9b5-2cec3e66f780", "code": "# initial_program.py\n\nimport random\n\n# EVOLVE-BLOCK-START\ndef run_search():\n    n = 47\n    # all grid points\n    grid = [(x,y) for x in range(n) for y in range(n)]\n    S = []\n    #random.shuffle(grid) # Remove shuffling for better initial distribution\n    for (x,y) in grid:\n        ok = True\n        # check collinearity against every pair already in S\n        for i in range(len(S)):\n            for j in range(i + 1, len(S)):\n                x1, y1 = S[i]\n                x2, y2 = S[j]\n                # Check if (x, y), (x1, y1), and (x2, y2) are collinear\n                if (y - y1) * (x2 - x1) == (y2 - y1) * (x - x1):\n                    ok = False\n                    break\n            if not ok:\n                break\n\n        if ok:\n            S.append((x,y))\n    return S\n# EVOLVE-BLOCK-END ", "language": "python", "parent_id": "e8158e7a-e5fb-4e3d-bbfd-88332111ffd7", "generation": 4, "timestamp": 1748145627.1402714, "iteration_found": 46, "metrics": {"point_count": 65.0, "overall_score": 65.0, "runtime": 0.09479069709777832, "valid_solution": 1.0}, "complexity": 0.0, "diversity": 0.0, "metadata": {"changes": "Change 1: Replace 12 lines with 10 lines\nChange 2: Replace 22 lines with 20 lines", "parent_metrics": {"point_count": 69.0, "overall_score": 69.0, "runtime": 0.030051231384277344, "valid_solution": 1.0}}}