{"id": "5f5b8f12-6d6b-4e59-a691-d02f38cb7d86", "code": "# initial_program.py\n\nimport random\n\n# EVOLVE-BLOCK-START\ndef run_search():\n    n = 47\n    # all grid points\n    grid = [(x,y) for x in range(n) for y in range(n)]\n    S = []\n    random.shuffle(grid)\n    for (x,y) in grid:\n        ok = True\n        # check collinearity against every point already in S\n        for i in range(len(S)):\n            x1,y1 = S[i]\n            # check collinearity against every other point already in S\n            for j in range(i+1, len(S)):\n                x2,y2 = S[j]\n                # collinear iff (y2-y1)*(x - x1) == (y - y1)*(x2 - x1)\n                if (y2 - y1)*(x - x1) == (y - y1)*(x2 - x1):\n                    # Introduce a small chance to accept the point even if collinear\n                    if random.random() > 0.05:  # 5% chance to reject\n                        ok = False\n                        break\n            if not ok:\n                break\n        if ok:\n            S.append((x,y))\n    return S\n# EVOLVE-BLOCK-END ", "language": "python", "parent_id": "136f59ad-5509-4d60-b4b8-8d26676e77a6", "generation": 2, "timestamp": 1748144679.1380785, "iteration_found": 25, "metrics": {"point_count": 74.0, "overall_score": 0.0, "runtime": 0.17511677742004395, "valid_solution": 0.0}, "complexity": 0.0, "diversity": 0.0, "metadata": {"changes": "Change 1: Replace 4 lines with 6 lines", "parent_metrics": {"point_count": 71.0, "overall_score": 71.0, "runtime": 0.17279505729675293, "valid_solution": 1.0}}}